cc_clients_python_lib/__init__.py
cc_clients_python_lib/common.py
cc_clients_python_lib/constants.py
cc_clients_python_lib/environment_client.py
cc_clients_python_lib/flink_client.py
cc_clients_python_lib/http_status.py
cc_clients_python_lib/iam_client.py
cc_clients_python_lib/kafka_topic_client.py
cc_clients_python_lib/metrics_client.py
cc_clients_python_lib/py.typed
cc_clients_python_lib/schema_registry_client.py
cc_clients_python_lib/tableflow_client.py
cc_clients_python_lib/cc_openapi_v2_1/__init__.py
cc_clients_python_lib/cc_openapi_v2_1/openapi.json
cc_clients_python_lib/cc_openapi_v2_1/v2.py
cc_clients_python_lib/cc_openapi_v2_1/artifact/__init__.py
cc_clients_python_lib/cc_openapi_v2_1/artifact/v1/UploadSource.py
cc_clients_python_lib/cc_openapi_v2_1/artifact/v1/__init__.py
cc_clients_python_lib/cc_openapi_v2_1/billing/__init__.py
cc_clients_python_lib/cc_openapi_v2_1/billing/v1.py
cc_clients_python_lib/cc_openapi_v2_1/byok/__init__.py
cc_clients_python_lib/cc_openapi_v2_1/byok/v1.py
cc_clients_python_lib/cc_openapi_v2_1/ccl/__init__.py
cc_clients_python_lib/cc_openapi_v2_1/ccl/v1.py
cc_clients_python_lib/cc_openapi_v2_1/cdx/__init__.py
cc_clients_python_lib/cc_openapi_v2_1/cdx/v1.py
cc_clients_python_lib/cc_openapi_v2_1/cmk/__init__.py
cc_clients_python_lib/cc_openapi_v2_1/cmk/v2.py
cc_clients_python_lib/cc_openapi_v2_1/connect/__init__.py
cc_clients_python_lib/cc_openapi_v2_1/connect/v1/UploadSource.py
cc_clients_python_lib/cc_openapi_v2_1/connect/v1/__init__.py
cc_clients_python_lib/cc_openapi_v2_1/fcpm/__init__.py
cc_clients_python_lib/cc_openapi_v2_1/fcpm/v2.py
cc_clients_python_lib/cc_openapi_v2_1/iam/__init__.py
cc_clients_python_lib/cc_openapi_v2_1/iam/v2/User.py
cc_clients_python_lib/cc_openapi_v2_1/iam/v2/__init__.py
cc_clients_python_lib/cc_openapi_v2_1/iam/v2/sso.py
cc_clients_python_lib/cc_openapi_v2_1/kafka_quotas/__init__.py
cc_clients_python_lib/cc_openapi_v2_1/kafka_quotas/v1.py
cc_clients_python_lib/cc_openapi_v2_1/ksqldbcm/__init__.py
cc_clients_python_lib-0.30.3.0.dist-info/METADATA
cc_clients_python_lib-0.30.3.0.dist-info/WHEEL
cc_clients_python_lib-0.30.3.0.dist-info/licenses/LICENSE.md
cc_clients_python_lib-0.30.3.0.dist-info/RECORD
