Metadata-Version: 2.4
Name: cc-clients-python_lib
Version: 0.30.3.0
Summary: Confluent Cloud Clients Python Library
Author-email: "Jeffrey Jonathan Jennings (J3)" <j3@thej3.com>
License-File: LICENSE.md
Requires-Python: >=3.11.9
Requires-Dist: attrs>=25.1.0
Requires-Dist: avro>=1.12.0
Requires-Dist: datamodel-code-generator>=0.28.4
Requires-Dist: dotenv>=0.9.9
Requires-Dist: fastavro>=1.10.0
Requires-Dist: httpx>=0.28.1
Requires-Dist: pydantic>=2.10.6
Requires-Dist: pytest>=8.3.4
Requires-Dist: python-dotenv>=1.1.0
Requires-Dist: requests>=2.32.3
Requires-Dist: setuptools>=75.8.0
Requires-Dist: urllib3>=2.3.0
Requires-Dist: wheel>=0.45.1
